dskmgr-0.0.3.data/data/share/man/man1/dskmgr.1
dskmgr-0.0.3.data/scripts/dskmgr
dskmgr-0.0.3.data/scripts/dskmgrd
libdskmgr/__init__.py
libdskmgr/common.py
libdskmgr/connection.py
libdskmgr/connection_handler.py
libdskmgr/desktop_manager.py
libdskmgr/exceptions.py
libdskmgr/server.py
libdskmgr/subscribers.py
libdskmgr/utils.py
libdskmgr/version.py
libdskmgr/scripts/__init__.py
libdskmgr/scripts/main.py
libdskmgr/wm/__init__.py
libdskmgr/wm/bspwm.py
libdskmgr/wm/bspwm_mock.py
libdskmgr/wm/wm.py
libdskmgr/wm/wm_factory.py
dskmgr-0.0.3.dist-info/LICENSE
dskmgr-0.0.3.dist-info/METADATA
dskmgr-0.0.3.dist-info/WHEEL
dskmgr-0.0.3.dist-info/top_level.txt
dskmgr-0.0.3.dist-info/RECORD
